LICENSE
README.rst
setup.cfg
setup.py
PyLTI1p3_Belovolov.egg-info/PKG-INFO
PyLTI1p3_Belovolov.egg-info/SOURCES.txt
PyLTI1p3_Belovolov.egg-info/dependency_links.txt
PyLTI1p3_Belovolov.egg-info/not-zip-safe
PyLTI1p3_Belovolov.egg-info/requires.txt
PyLTI1p3_Belovolov.egg-info/top_level.txt
pylti1p3/__init__.py
pylti1p3/actions.py
pylti1p3/assignments_grades.py
pylti1p3/cookie.py
pylti1p3/cookies_allowed_check.py
pylti1p3/course_groups.py
pylti1p3/deep_link.py
pylti1p3/deep_link_resource.py
pylti1p3/deployment.py
pylti1p3/exception.py
pylti1p3/grade.py
pylti1p3/lineitem.py
pylti1p3/message_launch.py
pylti1p3/names_roles.py
pylti1p3/oidc_login.py
pylti1p3/redirect.py
pylti1p3/registration.py
pylti1p3/request.py
pylti1p3/roles.py
pylti1p3/service_connector.py
pylti1p3/session.py
pylti1p3/utils.py
pylti1p3/contrib/__init__.py
pylti1p3/contrib/django/__init__.py
pylti1p3/contrib/django/cookie.py
pylti1p3/contrib/django/message_launch.py
pylti1p3/contrib/django/oidc_login.py
pylti1p3/contrib/django/redirect.py
pylti1p3/contrib/django/request.py
pylti1p3/contrib/django/session.py
pylti1p3/contrib/django/launch_data_storage/__init__.py
pylti1p3/contrib/django/launch_data_storage/cache.py
pylti1p3/contrib/django/lti1p3_tool_config/__init__.py
pylti1p3/contrib/django/lti1p3_tool_config/admin.py
pylti1p3/contrib/django/lti1p3_tool_config/apps.py
pylti1p3/contrib/django/lti1p3_tool_config/models.py
pylti1p3/contrib/django/lti1p3_tool_config/migrations/0001_initial.py
pylti1p3/contrib/django/lti1p3_tool_config/migrations/__init__.py
pylti1p3/contrib/flask/__init__.py
pylti1p3/contrib/flask/cookie.py
pylti1p3/contrib/flask/message_launch.py
pylti1p3/contrib/flask/oidc_login.py
pylti1p3/contrib/flask/redirect.py
pylti1p3/contrib/flask/request.py
pylti1p3/contrib/flask/session.py
pylti1p3/contrib/flask/launch_data_storage/__init__.py
pylti1p3/contrib/flask/launch_data_storage/cache.py
pylti1p3/launch_data_storage/__init__.py
pylti1p3/launch_data_storage/base.py
pylti1p3/launch_data_storage/cache.py
pylti1p3/launch_data_storage/session.py
pylti1p3/message_validators/__init__.py
pylti1p3/message_validators/abstract.py
pylti1p3/message_validators/deep_link.py
pylti1p3/message_validators/privacy_launch.py
